manipylate/__init__.py
manipylate/flycheck_manipylate_classes.py
manipylate/manipylate_classes.py
manipylate-0.1.4.dist-info/LICENSE.txt
manipylate-0.1.4.dist-info/METADATA
manipylate-0.1.4.dist-info/WHEEL
manipylate-0.1.4.dist-info/top_level.txt
manipylate-0.1.4.dist-info/RECORD
