Metadata-Version: 2.1
Name: manipylate
Version: 0.1.4
Summary: Manipulate like plotting in python
Home-page: https://github.com/bottom-bracket/manipylate
Author: Philip Heringlake
Author-email: heringlake-public@mailbox.org
License: MIT
Project-URL: Source, https://github.com/bottom-bracket/manipylate
Platform: any
Classifier: Development Status :: 4 - Beta
Classifier: Programming Language :: Python
License-File: LICENSE.txt
Requires-Dist: importlib-metadata ; python_version < "3.8"
Provides-Extra: testing
Requires-Dist: setuptools ; extra == 'testing'
Requires-Dist: pytest ; extra == 'testing'
Requires-Dist: pytest-cov ; extra == 'testing'
